{
	"objects": [
		{
			"type": "pointreverb",
			"id": "0",
			"channels": "0",
			"group": "0",
			"priority": "0",
			"level": "0.0018623762",
			"position": {
				"az": "2.00000",
				"el": "-0.00000",
				"radius": "1.00000"
			},
			"biquadsos": [
				{
					"b0": "1.00000e+00",
					"b1": "0.00000e+00",
					"b2": "0.00000e+00",
					"a0": "1.00000e+00",
					"a1": "-3.99681e-01",
					"a2": "6.79630e-01"
				},
				{
					"b0": "1.00000e+00",
					"b1": "0.00000e+00",
					"b2": "0.00000e+00",
					"a0": "1.00000e+00",
					"a1": "-1.43283e+00",
					"a2": "6.81916e-01"
				},
				{
					"b0": "1.00000e+00",
					"b1": "0.00000e+00",
					"b2": "0.00000e+00",
					"a0": "1.00000e+00",
					"a1": "-8.85752e-01",
					"a2": "7.01966e-01"
				},
				{
					"b0": "1.00000e+00",
					"b1": "0.00000e+00",
					"b2": "0.00000e+00",
					"a0": "1.00000e+00",
					"a1": "2.58302e-01",
					"a2": "7.03654e-01"
				},
				{
					"b0": "1.00000e+00",
					"b1": "0.00000e+00",
					"b2": "0.00000e+00",
					"a0": "1.00000e+00",
					"a1": "-1.63462e+00",
					"a2": "7.08050e-01"
				},
				{
					"b0": "1.00000e+00",
					"b1": "0.00000e+00",
					"b2": "0.00000e+00",
					"a0": "1.00000e+00",
					"a1": "8.09670e-01",
					"a2": "7.39421e-01"
				},
				{
					"b0": "1.00000e+00",
					"b1": "0.00000e+00",
					"b2": "0.00000e+00",
					"a0": "1.00000e+00",
					"a1": "1.33762e+00",
					"a2": "7.70801e-01"
				},
				{
					"b0": "1.00000e+00",
					"b1": "0.00000e+00",
					"b2": "0.00000e+00",
					"a0": "1.00000e+00",
					"a1": "1.71619e+00",
					"a2": "8.56018e-01"
				}
			],
			"room": {
				"ereflect": [
					{
						"level": "0.0004966167",
						"delay": "0.03451",
						"position": {
							"az": "182.00000",
							"el": "-33.00000",
							"refdist": "1.00000"
						},
						"biquadsos": [
							{
								"b0": "1.00000e+00",
								"b1": "0.00000e+00",
								"b2": "0.00000e+00",
								"a0": "1.00000e+00",
								"a1": "-1.28402e+00",
								"a2": "4.05642e-01"
							},
							{
								"b0": "1.00000e+00",
								"b1": "0.00000e+00",
								"b2": "0.00000e+00",
								"a0": "1.00000e+00",
								"a1": "-5.40475e-01",
								"a2": "4.05728e-01"
							},
							{
								"b0": "1.00000e+00",
								"b1": "0.00000e+00",
								"b2": "0.00000e+00",
								"a0": "1.00000e+00",
								"a1": "3.64982e-01",
								"a2": "6.15375e-01"
							},
							{
								"b0": "1.00000e+00",
								"b1": "0.00000e+00",
								"b2": "0.00000e+00",
								"a0": "1.00000e+00",
								"a1": "1.41866e+00",
								"a2": "6.80930e-01"
							}
						]
					},
					{
						"level": "0.0002865454",
						"delay": "0.03846",
						"position": {
							"az": "232.00000",
							"el": "-0.00000",
							"refdist": "1.00000"
						},
						"biquadsos": [
							{
								"b0": "1.00000e+00",
								"b1": "0.00000e+00",
								"b2": "0.00000e+00",
								"a0": "1.00000e+00",
								"a1": "-1.33654e+00",
								"a2": "4.52482e-01"
							},
							{
								"b0": "1.00000e+00",
								"b1": "0.00000e+00",
								"b2": "0.00000e+00",
								"a0": "1.00000e+00",
								"a1": "-6.03440e-01",
								"a2": "4.80644e-01"
							},
							{
								"b0": "1.00000e+00",
								"b1": "0.00000e+00",
								"b2": "0.00000e+00",
								"a0": "1.00000e+00",
								"a1": "3.78055e-01",
								"a2": "6.00768e-01"
							},
							{
								"b0": "1.00000e+00",
								"b1": "0.00000e+00",
								"b2": "0.00000e+00",
								"a0": "1.00000e+00",
								"a1": "1.38596e+00",
								"a2": "6.23984e-01"
							}
						]
					}
				],
				"lreverb": {
					"delay": "0.04269",
					"level": "0.00029, 0.00029, 0.00029, 0.00029, 0.00029, 0.00029, 0.00029, 0.00029, 0.00029",
					"attacktime": "0.00000, 0.00000, 0.00000, 0.00000, 0.00000, 0.00000, 0.00000, 0.00000, 0.00000",
					"decayconst": "-0.00017, -0.00018, -0.00025, -0.00035, -0.00024, -0.00036, -0.00038, -0.00055, -0.00109"
				}
			}
		},
		{
			"type": "pointreverb",
			"id": "0",
			"channels": "0",
			"group": "0",
			"priority": "0",
			"level": "0.0016186563",
			"position": {
				"az": "340.00000",
				"el": "-0.00000",
				"radius": "1.00000"
			},
			"biquadsos": [
				{
					"b0": "1.00000e+00",
					"b1": "0.00000e+00",
					"b2": "0.00000e+00",
					"a0": "1.00000e+00",
					"a1": "2.70858e-01",
					"a2": "6.56280e-01"
				},
				{
					"b0": "1.00000e+00",
					"b1": "0.00000e+00",
					"b2": "0.00000e+00",
					"a0": "1.00000e+00",
					"a1": "-3.25925e-01",
					"a2": "6.63158e-01"
				},
				{
					"b0": "1.00000e+00",
					"b1": "0.00000e+00",
					"b2": "0.00000e+00",
					"a0": "1.00000e+00",
					"a1": "-1.38855e+00",
					"a2": "6.64815e-01"
				},
				{
					"b0": "1.00000e+00",
					"b1": "0.00000e+00",
					"b2": "0.00000e+00",
					"a0": "1.00000e+00",
					"a1": "1.35349e+00",
					"a2": "7.12964e-01"
				},
				{
					"b0": "1.00000e+00",
					"b1": "0.00000e+00",
					"b2": "0.00000e+00",
					"a0": "1.00000e+00",
					"a1": "-8.64108e-01",
					"a2": "7.18276e-01"
				},
				{
					"b0": "1.00000e+00",
					"b1": "0.00000e+00",
					"b2": "0.00000e+00",
					"a0": "1.00000e+00",
					"a1": "-1.64191e+00",
					"a2": "7.21015e-01"
				},
				{
					"b0": "1.00000e+00",
					"b1": "0.00000e+00",
					"b2": "0.00000e+00",
					"a0": "1.00000e+00",
					"a1": "8.24672e-01",
					"a2": "7.31888e-01"
				},
				{
					"b0": "1.00000e+00",
					"b1": "0.00000e+00",
					"b2": "0.00000e+00",
					"a0": "1.00000e+00",
					"a1": "1.76412e+00",
					"a2": "8.48538e-01"
				}
			],
			"room": {
				"ereflect": [
					{
						"level": "0.0004911582",
						"delay": "0.03400",
						"position": {
							"az": "200.00000",
							"el": "-33.00000",
							"refdist": "1.00000"
						},
						"biquadsos": [
							{
								"b0": "1.00000e+00",
								"b1": "0.00000e+00",
								"b2": "0.00000e+00",
								"a0": "1.00000e+00",
								"a1": "-1.16389e+00",
								"a2": "3.83255e-01"
							},
							{
								"b0": "1.00000e+00",
								"b1": "0.00000e+00",
								"b2": "0.00000e+00",
								"a0": "1.00000e+00",
								"a1": "-5.47028e-01",
								"a2": "4.43982e-01"
							},
							{
								"b0": "1.00000e+00",
								"b1": "0.00000e+00",
								"b2": "0.00000e+00",
								"a0": "1.00000e+00",
								"a1": "3.69478e-01",
								"a2": "4.93141e-01"
							},
							{
								"b0": "1.00000e+00",
								"b1": "0.00000e+00",
								"b2": "0.00000e+00",
								"a0": "1.00000e+00",
								"a1": "1.31463e+00",
								"a2": "6.08449e-01"
							}
						]
					},
					{
						"level": "0.0002325188",
						"delay": "0.03811",
						"position": {
							"az": "225.00000",
							"el": "-27.00000",
							"refdist": "1.00000"
						},
						"biquadsos": [
							{
								"b0": "1.00000e+00",
								"b1": "0.00000e+00",
								"b2": "0.00000e+00",
								"a0": "1.00000e+00",
								"a1": "-1.08143e+00",
								"a2": "2.68458e-01"
							},
							{
								"b0": "1.00000e+00",
								"b1": "0.00000e+00",
								"b2": "0.00000e+00",
								"a0": "1.00000e+00",
								"a1": "-7.42090e-01",
								"a2": "4.21750e-01"
							},
							{
								"b0": "1.00000e+00",
								"b1": "0.00000e+00",
								"b2": "0.00000e+00",
								"a0": "1.00000e+00",
								"a1": "3.02034e-01",
								"a2": "5.78503e-01"
							},
							{
								"b0": "1.00000e+00",
								"b1": "0.00000e+00",
								"b2": "0.00000e+00",
								"a0": "1.00000e+00",
								"a1": "1.30801e+00",
								"a2": "6.19749e-01"
							}
						]
					}
				],
				"lreverb": {
					"delay": "0.04405",
					"level": "0.00034, 0.00034, 0.00034, 0.00034, 0.00034, 0.00034, 0.00034, 0.00034, 0.00034",
					"attacktime": "0.00000, 0.00000, 0.00000, 0.00000, 0.00000, 0.00000, 0.00000, 0.00000, 0.00000",
					"decayconst": "-0.00013, -0.00013, -0.00013, -0.00016, -0.00020, -0.00030, -0.00028, -0.00070, -0.00121"
				}
			}
		},
		{
			"type": "pointreverb",
			"id": "0",
			"channels": "0",
			"group": "0",
			"priority": "0",
			"level": "0.0017287234",
			"position": {
				"az": "26.00000",
				"el": "-0.00000",
				"radius": "1.00000"
			},
			"biquadsos": [
				{
					"b0": "1.00000e+00",
					"b1": "0.00000e+00",
					"b2": "0.00000e+00",
					"a0": "1.00000e+00",
					"a1": "-1.39971e+00",
					"a2": "6.52878e-01"
				},
				{
					"b0": "1.00000e+00",
					"b1": "0.00000e+00",
					"b2": "0.00000e+00",
					"a0": "1.00000e+00",
					"a1": "-1.59068e+00",
					"a2": "6.78886e-01"
				},
				{
					"b0": "1.00000e+00",
					"b1": "0.00000e+00",
					"b2": "0.00000e+00",
					"a0": "1.00000e+00",
					"a1": "-3.24298e-01",
					"a2": "6.88693e-01"
				},
				{
					"b0": "1.00000e+00",
					"b1": "0.00000e+00",
					"b2": "0.00000e+00",
					"a0": "1.00000e+00",
					"a1": "3.34233e-01",
					"a2": "6.94613e-01"
				},
				{
					"b0": "1.00000e+00",
					"b1": "0.00000e+00",
					"b2": "0.00000e+00",
					"a0": "1.00000e+00",
					"a1": "1.33293e+00",
					"a2": "6.96926e-01"
				},
				{
					"b0": "1.00000e+00",
					"b1": "0.00000e+00",
					"b2": "0.00000e+00",
					"a0": "1.00000e+00",
					"a1": "-8.57846e-01",
					"a2": "7.16054e-01"
				},
				{
					"b0": "1.00000e+00",
					"b1": "0.00000e+00",
					"b2": "0.00000e+00",
					"a0": "1.00000e+00",
					"a1": "8.90519e-01",
					"a2": "7.24159e-01"
				},
				{
					"b0": "1.00000e+00",
					"b1": "0.00000e+00",
					"b2": "0.00000e+00",
					"a0": "1.00000e+00",
					"a1": "1.76953e+00",
					"a2": "8.52441e-01"
				}
			],
			"room": {
				"ereflect": [
					{
						"level": "0.0004056083",
						"delay": "0.03572",
						"position": {
							"az": "164.00000",
							"el": "-35.00000",
							"refdist": "1.00000"
						},
						"biquadsos": [
							{
								"b0": "1.00000e+00",
								"b1": "0.00000e+00",
								"b2": "0.00000e+00",
								"a0": "1.00000e+00",
								"a1": "-3.46332e-01",
								"a2": "3.55659e-01"
							},
							{
								"b0": "1.00000e+00",
								"b1": "0.00000e+00",
								"b2": "0.00000e+00",
								"a0": "1.00000e+00",
								"a1": "-1.28899e+00",
								"a2": "4.75498e-01"
							},
							{
								"b0": "1.00000e+00",
								"b1": "0.00000e+00",
								"b2": "0.00000e+00",
								"a0": "1.00000e+00",
								"a1": "3.87598e-01",
								"a2": "5.22064e-01"
							},
							{
								"b0": "1.00000e+00",
								"b1": "0.00000e+00",
								"b2": "0.00000e+00",
								"a0": "1.00000e+00",
								"a1": "1.31690e+00",
								"a2": "6.12317e-01"
							}
						]
					},
					{
						"level": "0.0002234435",
						"delay": "0.04038",
						"position": {
							"az": "29.00000",
							"el": "-55.00000",
							"refdist": "1.00000"
						},
						"biquadsos": [
							{
								"b0": "1.00000e+00",
								"b1": "0.00000e+00",
								"b2": "0.00000e+00",
								"a0": "1.00000e+00",
								"a1": "-1.13009e+00",
								"a2": "3.32639e-01"
							},
							{
								"b0": "1.00000e+00",
								"b1": "0.00000e+00",
								"b2": "0.00000e+00",
								"a0": "1.00000e+00",
								"a1": "-5.71277e-01",
								"a2": "3.88394e-01"
							},
							{
								"b0": "1.00000e+00",
								"b1": "0.00000e+00",
								"b2": "0.00000e+00",
								"a0": "1.00000e+00",
								"a1": "2.79337e-01",
								"a2": "5.18668e-01"
							},
							{
								"b0": "1.00000e+00",
								"b1": "0.00000e+00",
								"b2": "0.00000e+00",
								"a0": "1.00000e+00",
								"a1": "1.31767e+00",
								"a2": "6.18067e-01"
							}
						]
					}
				],
				"lreverb": {
					"delay": "0.04509",
					"level": "0.00037, 0.00037, 0.00037, 0.00037, 0.00037, 0.00037, 0.00037, 0.00037, 0.00037",
					"attacktime": "0.00000, 0.00000, 0.00000, 0.00000, 0.00000, 0.00000, 0.00000, 0.00000, 0.00000",
					"decayconst": "-0.00013, -0.00013, -0.00013, -0.00018, -0.00019, -0.00029, -0.00032, -0.00071, -0.00168"
				}
			}
		},
		{
			"type": "pointreverb",
			"id": "0",
			"channels": "0",
			"group": "0",
			"priority": "0",
			"level": "0.0057013625",
			"position": {
				"az": "268.00000",
				"el": "-0.00000",
				"radius": "1.00000"
			},
			"biquadsos": [
				{
					"b0": "1.00000e+00",
					"b1": "0.00000e+00",
					"b2": "0.00000e+00",
					"a0": "1.00000e+00",
					"a1": "3.19225e-01",
					"a2": "6.04149e-01"
				},
				{
					"b0": "1.00000e+00",
					"b1": "0.00000e+00",
					"b2": "0.00000e+00",
					"a0": "1.00000e+00",
					"a1": "-3.18695e-01",
					"a2": "6.23457e-01"
				},
				{
					"b0": "1.00000e+00",
					"b1": "0.00000e+00",
					"b2": "0.00000e+00",
					"a0": "1.00000e+00",
					"a1": "-8.00832e-01",
					"a2": "6.35564e-01"
				},
				{
					"b0": "1.00000e+00",
					"b1": "0.00000e+00",
					"b2": "0.00000e+00",
					"a0": "1.00000e+00",
					"a1": "1.30623e+00",
					"a2": "6.93698e-01"
				},
				{
					"b0": "1.00000e+00",
					"b1": "0.00000e+00",
					"b2": "0.00000e+00",
					"a0": "1.00000e+00",
					"a1": "7.68319e-01",
					"a2": "6.94299e-01"
				},
				{
					"b0": "1.00000e+00",
					"b1": "0.00000e+00",
					"b2": "0.00000e+00",
					"a0": "1.00000e+00",
					"a1": "-1.68948e+00",
					"a2": "7.26468e-01"
				},
				{
					"b0": "1.00000e+00",
					"b1": "0.00000e+00",
					"b2": "0.00000e+00",
					"a0": "1.00000e+00",
					"a1": "-1.33740e+00",
					"a2": "7.26487e-01"
				},
				{
					"b0": "1.00000e+00",
					"b1": "0.00000e+00",
					"b2": "0.00000e+00",
					"a0": "1.00000e+00",
					"a1": "1.75981e+00",
					"a2": "8.55509e-01"
				}
			],
			"room": {
				"ereflect": [
					{
						"level": "0.0004687127",
						"delay": "0.03271",
						"position": {
							"az": "299.00000",
							"el": "-66.00000",
							"refdist": "1.00000"
						},
						"biquadsos": [
							{
								"b0": "1.00000e+00",
								"b1": "0.00000e+00",
								"b2": "0.00000e+00",
								"a0": "1.00000e+00",
								"a1": "-3.47727e-01",
								"a2": "-6.14079e-01"
							},
							{
								"b0": "1.00000e+00",
								"b1": "0.00000e+00",
								"b2": "0.00000e+00",
								"a0": "1.00000e+00",
								"a1": "1.11303e-01",
								"a2": "5.19893e-01"
							},
							{
								"b0": "1.00000e+00",
								"b1": "0.00000e+00",
								"b2": "0.00000e+00",
								"a0": "1.00000e+00",
								"a1": "-8.75114e-01",
								"a2": "5.72704e-01"
							},
							{
								"b0": "1.00000e+00",
								"b1": "0.00000e+00",
								"b2": "0.00000e+00",
								"a0": "1.00000e+00",
								"a1": "1.08630e+00",
								"a2": "5.84857e-01"
							}
						]
					},
					{
						"level": "0.0002909301",
						"delay": "0.03672",
						"position": {
							"az": "98.00000",
							"el": "-43.00000",
							"refdist": "1.00000"
						},
						"biquadsos": [
							{
								"b0": "1.00000e+00",
								"b1": "0.00000e+00",
								"b2": "0.00000e+00",
								"a0": "1.00000e+00",
								"a1": "-1.08353e+00",
								"a2": "1.28901e-01"
							},
							{
								"b0": "1.00000e+00",
								"b1": "0.00000e+00",
								"b2": "0.00000e+00",
								"a0": "1.00000e+00",
								"a1": "-7.94821e-01",
								"a2": "5.33645e-01"
							},
							{
								"b0": "1.00000e+00",
								"b1": "0.00000e+00",
								"b2": "0.00000e+00",
								"a0": "1.00000e+00",
								"a1": "3.49746e-01",
								"a2": "5.89120e-01"
							},
							{
								"b0": "1.00000e+00",
								"b1": "0.00000e+00",
								"b2": "0.00000e+00",
								"a0": "1.00000e+00",
								"a1": "1.35430e+00",
								"a2": "6.19028e-01"
							}
						]
					}
				],
				"lreverb": {
					"delay": "0.03961",
					"level": "0.00055, 0.00055, 0.00055, 0.00055, 0.00055, 0.00055, 0.00055, 0.00055, 0.00055",
					"attacktime": "0.00000, 0.00000, 0.00000, 0.00000, 0.00000, 0.00000, 0.00000, 0.00000, 0.00000",
					"decayconst": "-0.00053, -0.00060, -0.00069, -0.00093, -0.00066, -0.00068, -0.00090, -0.00106, -0.00154"
				}
			}
		},
		{
			"type": "pointreverb",
			"id": "0",
			"channels": "0",
			"group": "0",
			"priority": "0",
			"level": "0.0026225670",
			"position": {
				"az": "97.00000",
				"el": "-0.00000",
				"radius": "1.00000"
			},
			"biquadsos": [
				{
					"b0": "1.00000e+00",
					"b1": "0.00000e+00",
					"b2": "0.00000e+00",
					"a0": "1.00000e+00",
					"a1": "-1.28637e+00",
					"a2": "6.28793e-01"
				},
				{
					"b0": "1.00000e+00",
					"b1": "0.00000e+00",
					"b2": "0.00000e+00",
					"a0": "1.00000e+00",
					"a1": "2.37075e-01",
					"a2": "6.34656e-01"
				},
				{
					"b0": "1.00000e+00",
					"b1": "0.00000e+00",
					"b2": "0.00000e+00",
					"a0": "1.00000e+00",
					"a1": "-8.60796e-01",
					"a2": "6.52039e-01"
				},
				{
					"b0": "1.00000e+00",
					"b1": "0.00000e+00",
					"b2": "0.00000e+00",
					"a0": "1.00000e+00",
					"a1": "-3.63827e-01",
					"a2": "6.74763e-01"
				},
				{
					"b0": "1.00000e+00",
					"b1": "0.00000e+00",
					"b2": "0.00000e+00",
					"a0": "1.00000e+00",
					"a1": "-1.65365e+00",
					"a2": "6.95656e-01"
				},
				{
					"b0": "1.00000e+00",
					"b1": "0.00000e+00",
					"b2": "0.00000e+00",
					"a0": "1.00000e+00",
					"a1": "8.15241e-01",
					"a2": "7.06884e-01"
				},
				{
					"b0": "1.00000e+00",
					"b1": "0.00000e+00",
					"b2": "0.00000e+00",
					"a0": "1.00000e+00",
					"a1": "1.35154e+00",
					"a2": "7.54894e-01"
				},
				{
					"b0": "1.00000e+00",
					"b1": "0.00000e+00",
					"b2": "0.00000e+00",
					"a0": "1.00000e+00",
					"a1": "1.73861e+00",
					"a2": "8.29201e-01"
				}
			],
			"room": {
				"ereflect": [
					{
						"level": "0.0002053234",
						"delay": "0.03183",
						"position": {
							"az": "105.00000",
							"el": "-0.00000",
							"refdist": "1.00000"
						},
						"biquadsos": [
							{
								"b0": "1.00000e+00",
								"b1": "0.00000e+00",
								"b2": "0.00000e+00",
								"a0": "1.00000e+00",
								"a1": "-1.23786e+00",
								"a2": "2.77948e-01"
							},
							{
								"b0": "1.00000e+00",
								"b1": "0.00000e+00",
								"b2": "0.00000e+00",
								"a0": "1.00000e+00",
								"a1": "-6.64899e-01",
								"a2": "5.53950e-01"
							},
							{
								"b0": "1.00000e+00",
								"b1": "0.00000e+00",
								"b2": "0.00000e+00",
								"a0": "1.00000e+00",
								"a1": "4.54866e-01",
								"a2": "6.06498e-01"
							},
							{
								"b0": "1.00000e+00",
								"b1": "0.00000e+00",
								"b2": "0.00000e+00",
								"a0": "1.00000e+00",
								"a1": "1.35230e+00",
								"a2": "6.32773e-01"
							}
						]
					},
					{
						"level": "0.0001863329",
						"delay": "0.03439",
						"position": {
							"az": "105.00000",
							"el": "-66.00000",
							"refdist": "1.00000"
						},
						"biquadsos": [
							{
								"b0": "1.00000e+00",
								"b1": "0.00000e+00",
								"b2": "0.00000e+00",
								"a0": "1.00000e+00",
								"a1": "-1.16944e+00",
								"a2": "2.40952e-01"
							},
							{
								"b0": "1.00000e+00",
								"b1": "0.00000e+00",
								"b2": "0.00000e+00",
								"a0": "1.00000e+00",
								"a1": "2.33405e-01",
								"a2": "4.96812e-01"
							},
							{
								"b0": "1.00000e+00",
								"b1": "0.00000e+00",
								"b2": "0.00000e+00",
								"a0": "1.00000e+00",
								"a1": "-7.39397e-01",
								"a2": "5.10932e-01"
							},
							{
								"b0": "1.00000e+00",
								"b1": "0.00000e+00",
								"b2": "0.00000e+00",
								"a0": "1.00000e+00",
								"a1": "1.29451e+00",
								"a2": "5.97550e-01"
							}
						]
					}
				],
				"lreverb": {
					"delay": "0.03769",
					"level": "0.00048, 0.00048, 0.00048, 0.00048, 0.00048, 0.00048, 0.00048, 0.00048, 0.00048",
					"attacktime": "0.00000, 0.00000, 0.00000, 0.00000, 0.00000, 0.00000, 0.00000, 0.00000, 0.00000",
					"decayconst": "-0.00019, -0.00021, -0.00027, -0.00034, -0.00024, -0.00032, -0.00035, -0.00060, -0.00181"
				}
			}
		}
	]
}
